covid_surge/__init__.py
covid_surge/pylintrc
covid_surge/examples/run_countries.py
covid_surge/examples/run_country.py
covid_surge/examples/run_us_combined.py
covid_surge/examples/run_us_state.py
covid_surge/examples/run_us_state_counties.py
covid_surge/examples/run_us_states.py
covid_surge/examples/run_us_states_counties.py
covid_surge/src/surge.py
covid_surge/tests/test_countries.py
covid_surge/tests/test_us_combined.py
covid_surge/tests/test_us_state_counties.py
covid_surge/tests/test_us_states.py
covid_surge/tests/test_us_states_counties.py
covid_surge-0.0.41.dist-info/LICENSE
covid_surge-0.0.41.dist-info/METADATA
covid_surge-0.0.41.dist-info/WHEEL
covid_surge-0.0.41.dist-info/top_level.txt
covid_surge-0.0.41.dist-info/RECORD
