Metadata-Version: 2.1
Name: covid-surge
Version: 0.0.41
Summary: Covid-Surge is a utility for computing and comparing mortality surge periods of communities afflicted by the COVID-19 virus pandemic.
Home-page: https://github.com/dpploy/covid-surge
Author: Valmor F. de Almeida
Author-email: valmor_dealmeida@uml.edu
License: UNKNOWN
Platform: UNKNOWN
Classifier: Programming Language :: Python :: 3
Classifier: License :: OSI Approved :: GNU General Public License v3 (GPLv3)
Classifier: Topic :: Scientific/Engineering :: Mathematics
Classifier: Intended Audience :: Developers
Classifier: Intended Audience :: Education
Classifier: Intended Audience :: End Users/Desktop
Classifier: Intended Audience :: Science/Research
Classifier: Operating System :: MacOS
Classifier: Operating System :: Unix
Classifier: Topic :: Education
Classifier: Topic :: Utilities
Requires-Python: >=3.6
Requires-Dist: matplotlib
Requires-Dist: numpy
Requires-Dist: pandas
Requires-Dist: asserts
